[
    {
        "title": "Introduction to Web Development",
        "description": "A beginner-friendly seminar on the basics of HTML, CSS, and JavaScript.",
        "location": "Online",
        "speaker": "John Smith",
        "start_date": "2024-01-15T10:00:00.000Z",
        "end_date": "2024-01-15T12:00:00.000Z",
        "start_time": "2024-01-15T10:00:00.000Z",
        "end_time": "2024-01-15T12:00:00.000Z",
        "capacity": 50,
        "registration_deadline": "2024-01-10T00:00:00.000Z",
        "status": "Upcoming"
    },
    {
        "title": "Advanced JavaScript Concepts",
        "description": "Delve deeper into JavaScript with topics like closures, prototypes, and asynchronous programming.",
        "location": "New York",
        "speaker": "Jane Doe",
        "start_date": "2024-02-20T14:00:00.000Z",
        "end_date": "2024-02-20T16:00:00.000Z",
        "start_time": "2024-02-20T14:00:00.000Z",
        "end_time": "2024-02-20T16:00:00.000Z",
        "capacity": 30,
        "registration_deadline": "2024-02-15T00:00:00.000Z",
        "status": "Upcoming"
    },
    {
        "title": "Data Science with Python",
        "description": "Learn how to use Python libraries like NumPy and Pandas for data analysis.",
        "location": "San Francisco",
        "speaker": "Peter Jones",
        "start_date": "2023-11-05T09:00:00.000Z",
        "end_date": "2023-11-05T17:00:00.000Z",
        "start_time": "2023-11-05T09:00:00.000Z",
        "end_time": "2023-11-05T17:00:00.000Z",
        "capacity": 40,
        "registration_deadline": "2023-10-31T00:00:00.000Z",
        "status": "Completed"
    },
    {
        "title": "Mobile App Development with React Native",
        "description": "Build cross-platform mobile apps using React Native.",
        "location": "Online",
        "speaker": "Sarah Smith",
        "start_date": "2024-03-10T11:00:00.000Z",
        "end_date": "2024-03-10T13:00:00.000Z",
        "start_time": "2024-03-10T11:00:00.000Z",
        "end_time": "2024-03-10T13:00:00.000Z",
        "capacity": 60,
        "registration_deadline": "2024-03-05T00:00:00.000Z",
        "status": "Upcoming"
    },
    {
        "title": "Cybersecurity Fundamentals",
        "description": "An introduction to cybersecurity principles and practices.",
        "location": "London",
        "speaker": "David Lee",
        "start_date": "2023-12-15T15:00:00.000Z",
        "end_date": "2023-12-15T17:00:00.000Z",
        "start_time": "2023-12-15T15:00:00.000Z",
        "end_time": "2023-12-15T17:00:00.000Z",
        "capacity": 25,
        "registration_deadline": "2023-12-10T00:00:00.000Z",
        "status": "Completed"
    },
    {
        "title": "Cloud Computing with AWS",
        "description": "Learn the basics of cloud computing and AWS services.",
        "location": "Seattle",
        "speaker": "Emily Brown",
        "start_date": "2024-04-01T10:00:00.000Z",
        "end_date": "2024-04-01T12:00:00.000Z",
        "start_time": "2024-04-01T10:00:00.000Z",
        "end_time": "2024-04-01T12:00:00.000Z",
        "capacity": 35,
        "registration_deadline": "2024-03-25T00:00:00.000Z",
        "status": "Upcoming"
    },
    {
        "title": "Frontend Frameworks Comparison (React, Angular, Vue)",
        "description": "Explore the pros and cons of the three major frontend frameworks.",
        "location": "Online",
        "speaker": "Michael Gray",
        "start_date": "2024-05-10T14:00:00.000Z",
        "end_date": "2024-05-10T16:00:00.000Z",
        "start_time": "2024-05-10T14:00:00.000Z",
        "end_time": "2024-05-10T16:00:00.000Z",
        "capacity": 70,
        "registration_deadline": "2024-05-05T00:00:00.000Z",
        "status": "Upcoming"
    },
    {
        "title": "Backend Development with Node.js",
        "description": "Learn how to build server-side applications using Node.js and Express.",
        "location": "Austin",
        "speaker": "Olivia White",
        "start_date": "2024-02-28T09:30:00.000Z",
        "end_date": "2024-02-28T17:30:00.000Z",
        "start_time": "2024-02-28T09:30:00.000Z",
        "end_time": "2024-02-28T17:30:00.000Z",
        "capacity": 45,
        "registration_deadline": "2024-02-20T00:00:00.000Z",
        "status": "Upcoming"
    },
    {
        "title": "UI/UX Design Principles",
        "description": "An overview of essential UI/UX design principles for creating user-friendly interfaces.",
        "location": "Online",
        "speaker": "William Green",
        "start_date": "2024-06-15T11:30:00.000Z",
        "end_date": "2024-06-15T13:30:00.000Z",
        "start_time": "2024-06-15T11:30:00.000Z",
        "end_time": "2024-06-15T13:30:00.000Z",
        "capacity": 55,
        "registration_deadline": "2024-06-10T00:00:00.000Z",
        "status": "Upcoming"
    },
    {
        "title": "Introduction to Blockchain Technology",
        "description": "Learn about the fundamentals of blockchain and its applications.",
        "location": "Zurich",
        "speaker": "Sophia Black",
        "start_date": "2024-03-22T16:00:00.000Z",
        "end_date": "2024-03-22T18:00:00.000Z",
        "start_time": "2024-03-22T16:00:00.000Z",
        "end_time": "2024-03-22T18:00:00.000Z",
        "capacity": 20,
        "registration_deadline": "2024-03-15T00:00:00.000Z",
        "status": "Upcoming"
    }
]
